textx/__init__.py
textx/const.py
textx/exceptions.py
textx/export.py
textx/generators.py
textx/lang.py
textx/metamodel.py
textx/model.py
textx/model_params.py
textx/registration.py
textx/textx.tx
textx/cli/__init__.py
textx/cli/check.py
textx/cli/discover.py
textx/cli/generate.py
textx/cli/version.py
textx/scoping/__init__.py
textx/scoping/providers.py
textx/scoping/rrel.py
textx/scoping/tools.py
textx-4.2.1.dist-info/entry_points.txt
textx-4.2.1.dist-info/LICENSE.txt
textx-4.2.1.dist-info/WHEEL
textx-4.2.1.dist-info/METADATA
textx-4.2.1.dist-info/RECORD
